llama_cpp_py_sync/__init__.py
llama_cpp_py_sync/__main__.py
llama_cpp_py_sync/_cffi_bindings.py
llama_cpp_py_sync/_cli.py
llama_cpp_py_sync/_version.py
llama_cpp_py_sync/backends.py
llama_cpp_py_sync/embeddings.py
llama_cpp_py_sync/libggml-base.0.9.5.dylib
llama_cpp_py_sync/libggml-base.0.dylib
llama_cpp_py_sync/libggml-base.dylib
llama_cpp_py_sync/libggml-blas.0.9.5.dylib
llama_cpp_py_sync/libggml-blas.0.dylib
llama_cpp_py_sync/libggml-blas.dylib
llama_cpp_py_sync/libggml-cpu.0.9.5.dylib
llama_cpp_py_sync/libggml-cpu.0.dylib
llama_cpp_py_sync/libggml-cpu.dylib
llama_cpp_py_sync/libggml.0.9.5.dylib
llama_cpp_py_sync/libggml.0.dylib
llama_cpp_py_sync/libggml.dylib
llama_cpp_py_sync/libllama.0.0.1.dylib
llama_cpp_py_sync/libllama.0.dylib
llama_cpp_py_sync/libllama.dylib
llama_cpp_py_sync/llama.py
llama_cpp_py_sync/py.typed
llama_cpp_py_sync-0.7830.dist-info/licenses/LICENSE
llama_cpp_py_sync-0.7830.dist-info/METADATA
llama_cpp_py_sync-0.7830.dist-info/WHEEL
llama_cpp_py_sync-0.7830.dist-info/top_level.txt
llama_cpp_py_sync-0.7830.dist-info/RECORD
