Metadata-Version: 2.4
Name: llama-cpp-py-sync
Version: 0.7830
Summary: Auto-synchronized Python bindings for llama.cpp using CFFI ABI mode
Author-email: Faris Al-Zahrani <contact@fariszahrani.com>
Maintainer-email: Faris Al-Zahrani <contact@fariszahrani.com>
License: MIT
Project-URL: Homepage, https://github.com/FarisZahrani/llama-cpp-py-sync
Project-URL: Repository, https://github.com/FarisZahrani/llama-cpp-py-sync
Project-URL: Documentation, https://github.com/FarisZahrani/llama-cpp-py-sync#readme
Project-URL: Issues, https://github.com/FarisZahrani/llama-cpp-py-sync/issues
Keywords: llama,llama.cpp,llm,language-model,ai,machine-learning,gguf,inference,cffi,bindings
Classifier: Development Status :: 4 - Beta
Classifier: Intended Audience :: Developers
Classifier: Intended Audience :: Science/Research
Classifier: License :: OSI Approved :: MIT License
Classifier: Operating System :: OS Independent
Classifier: Operating System :: POSIX :: Linux
Classifier: Operating System :: MacOS :: MacOS X
Classifier: Operating System :: Microsoft :: Windows
Classifier: Programming Language :: Python :: 3
Classifier: Programming Language :: Python :: Implementation :: CPython
Classifier: Programming Language :: Python :: 3.8
Classifier: Programming Language :: Python :: 3.9
Classifier: Programming Language :: Python :: 3.10
Classifier: Programming Language :: Python :: 3.11
Classifier: Programming Language :: Python :: 3.12
Classifier: Topic :: Scientific/Engineering :: Artificial Intelligence
Requires-Python: >=3.8
License-File: LICENSE
Requires-Dist: cffi>=1.15.0
Requires-Dist: certifi>=2023.7.22
Requires-Dist: numpy>=1.20.0
Provides-Extra: dev
Requires-Dist: pytest>=7.0.0; extra == "dev"
Requires-Dist: pytest-cov>=4.0.0; extra == "dev"
Requires-Dist: black>=23.0.0; extra == "dev"
Requires-Dist: ruff>=0.1.0; extra == "dev"
Requires-Dist: mypy>=1.0.0; extra == "dev"
Dynamic: license-file
